pgfaux/__init__.py
pgfaux/analyze.py
pgfaux/exceptions.py
pgfaux/generate.py
pgfaux/linearize.py
pgfaux-0.5.dist-info/LICENSE
pgfaux-0.5.dist-info/METADATA
pgfaux-0.5.dist-info/WHEEL
pgfaux-0.5.dist-info/top_level.txt
pgfaux-0.5.dist-info/RECORD
