Metadata-Version: 2.1
Name: pgfaux
Version: 0.5
Summary: Helper utilities for manipulating pgf objects
Author-email: Laurette Marais <lmarais@csir.co.za>
Project-URL: Homepage, https://gitlab.com/lmarais/pgfaux
Requires-Python: >=3.7
License-File: LICENSE
Requires-Dist: graphviz
